odoo8_addon_vendor_consignment_stock-8.0.0.2.0.99.dev22-py3.8-nspkg.pth
odoo_addons/vendor_consignment_stock/README.rst
odoo_addons/vendor_consignment_stock/__init__.py
odoo_addons/vendor_consignment_stock/__openerp__.py
odoo_addons/vendor_consignment_stock/data/route.xml
odoo_addons/vendor_consignment_stock/i18n/ca.po
odoo_addons/vendor_consignment_stock/i18n/de.po
odoo_addons/vendor_consignment_stock/i18n/es.po
odoo_addons/vendor_consignment_stock/i18n/es_ES.po
odoo_addons/vendor_consignment_stock/i18n/es_MX.po
odoo_addons/vendor_consignment_stock/i18n/fi.po
odoo_addons/vendor_consignment_stock/i18n/fr.po
odoo_addons/vendor_consignment_stock/i18n/fr_FR.po
odoo_addons/vendor_consignment_stock/i18n/hr.po
odoo_addons/vendor_consignment_stock/i18n/hu.po
odoo_addons/vendor_consignment_stock/i18n/it.po
odoo_addons/vendor_consignment_stock/i18n/nl.po
odoo_addons/vendor_consignment_stock/i18n/nl_NL.po
odoo_addons/vendor_consignment_stock/i18n/pt_BR.po
odoo_addons/vendor_consignment_stock/i18n/pt_PT.po
odoo_addons/vendor_consignment_stock/i18n/ro.po
odoo_addons/vendor_consignment_stock/i18n/sk.po
odoo_addons/vendor_consignment_stock/i18n/sl.po
odoo_addons/vendor_consignment_stock/i18n/tr.po
odoo_addons/vendor_consignment_stock/i18n/tr_TR.po
odoo_addons/vendor_consignment_stock/i18n/vendor_consignment_stock.pot
odoo_addons/vendor_consignment_stock/i18n/zh_CN.po
odoo_addons/vendor_consignment_stock/model/__init__.py
odoo_addons/vendor_consignment_stock/model/procurement.py
odoo_addons/vendor_consignment_stock/model/purchase_order.py
odoo_addons/vendor_consignment_stock/model/rule.py
odoo_addons/vendor_consignment_stock/model/sale_order.py
odoo_addons/vendor_consignment_stock/model/warehouse.py
odoo_addons/vendor_consignment_stock/security/group.xml
odoo_addons/vendor_consignment_stock/static/description/icon.png
odoo_addons/vendor_consignment_stock/tests/__init__.py
odoo_addons/vendor_consignment_stock/tests/test_delivery_without_owner.py
odoo8_addon_vendor_consignment_stock-8.0.0.2.0.99.dev22.dist-info/METADATA
odoo8_addon_vendor_consignment_stock-8.0.0.2.0.99.dev22.dist-info/WHEEL
odoo8_addon_vendor_consignment_stock-8.0.0.2.0.99.dev22.dist-info/namespace_packages.txt
odoo8_addon_vendor_consignment_stock-8.0.0.2.0.99.dev22.dist-info/top_level.txt
odoo8_addon_vendor_consignment_stock-8.0.0.2.0.99.dev22.dist-info/RECORD
