Metadata-Version: 2.1
Name: odoo8-addon-vendor-consignment-stock
Version: 8.0.0.2.0.99.dev22
Summary: Manage stock in our warehouse that is owned by a vendor
Home-page: UNKNOWN
Author: Camptocamp,Odoo Community Association (OCA)
Author-email: support@odoo-community.org
License: AGPL-3
Platform: UNKNOWN
Classifier: Programming Language :: Python
Classifier: Framework :: Odoo
Classifier: Framework :: Odoo :: 8.0
Classifier: License :: OSI Approved :: GNU Affero General Public License v3
Requires-Python: ~=2.7
Requires-Dist: odoo8-addon-sale-owner-stock-sourcing
Requires-Dist: odoo8-addon-stock-ownership-availability-rules
Requires-Dist: odoo (<9.0a,>=8.0a)
